<keymap version="1" name="Primary_OSX" parent="Mac OS X 10.5+">
  <action id="ActivateProjectToolWindow">
    <keyboard-shortcut first-keystroke="alt 1" />
  </action>
  <action id="ActivateStructureToolWindow" />
  <action id="InsertLiveTemplate">
    <keyboard-shortcut first-keystroke="shift meta l" />
  </action>
  <action id="MoveEditorToOppositeTabGroup">
    <keyboard-shortcut first-keystroke="alt m" second-keystroke="o" />
  </action>
  <action id="MoveTabDown">
    <keyboard-shortcut first-keystroke="alt m" second-keystroke="d" />
  </action>
  <action id="MoveTabRight">
    <keyboard-shortcut first-keystroke="alt m" second-keystroke="r" />
  </action>
  <action id="NextTab">
    <keyboard-shortcut first-keystroke="shift meta close_bracket" />
    <keyboard-shortcut first-keystroke="ctrl right" />
    <keyboard-shortcut first-keystroke="ctrl semicolon" />
  </action>
  <action id="PreviousTab">
    <keyboard-shortcut first-keystroke="shift meta open_bracket" />
    <keyboard-shortcut first-keystroke="ctrl left" />
    <keyboard-shortcut first-keystroke="ctrl j" />
  </action>
  <action id="QuickJavaDoc">
    <keyboard-shortcut first-keystroke="f1" />
    <mouse-shortcut keystroke="control button2" />
    <keyboard-shortcut first-keystroke="shift meta j" />
  </action>
  <action id="Resume">
    <keyboard-shortcut first-keystroke="meta alt r" />
    <keyboard-shortcut first-keystroke="f9" />
  </action>
  <action id="ShowProjectStructureSettings" />
  <action id="SplitHorizontally">
    <keyboard-shortcut first-keystroke="alt m" second-keystroke="h" />
  </action>
  <action id="SplitVertically">
    <keyboard-shortcut first-keystroke="alt m" second-keystroke="v" />
  </action>
</keymap>